<?xml version="1.0" encoding="UTF-8"?>
<metadata xml:lang="en"><Esri><CreaDate>20170616</CreaDate><CreaTime>17145700</CreaTime><ArcGISFormat>1.0</ArcGISFormat><SyncOnce>TRUE</SyncOnce><DataProperties><itemProps><itemLocation><linkage Sync="TRUE">file://\\Mac\Home\Documents\Honours\Data\Paleogeography\Paleotopo_shapes\Tectonic_uplift\Tectonic_uplift_ausantCopy</linkage><protocol Sync="TRUE">Local Area Network</protocol></itemLocation></itemProps><copyHistory><copy source="\\Mac\Home\Documents\Honours\Data\Paleogeography\Paleotopo_shapes\Tectonic_uplift\Tectonic_uplift_ausant" dest="\\Mac\Home\Documents\Honours\Data\Paleogeography\Paleotopo_shapes\Tectonic_uplift\Tectonic_uplift_ausantCopy" date="20170616" time="17145700"></copy></copyHistory></DataProperties></Esri></metadata>
